AUTHORS.rst
CONTRIBUTING.rst
HISTORY.rst
LICENSE
MANIFEST.in
README.rst
setup.cfg
setup.py
django_json_widget/__init__.py
django_json_widget/apps.py
django_json_widget/models.py
django_json_widget/urls.py
django_json_widget/views.py
django_json_widget/widgets.py
django_json_widget/static/css/django_json_widget.css
django_json_widget/static/dist/jsoneditor.min.css
django_json_widget/static/dist/jsoneditor.min.js
django_json_widget/static/dist/img/jsoneditor-icons.svg
django_json_widget/templates/django_json_widget.html
django_json_widget_copy.egg-info/PKG-INFO
django_json_widget_copy.egg-info/SOURCES.txt
django_json_widget_copy.egg-info/dependency_links.txt
django_json_widget_copy.egg-info/not-zip-safe
django_json_widget_copy.egg-info/requires.txt
django_json_widget_copy.egg-info/top_level.txt