Metadata-Version: 1.1
Name: django-json-widget-copy
Version: 0.2.0
Summary: Django json widget is an alternative widget that makes it easy to edit the jsonfield field of django.
Home-page: https://github.com/jmrivas86/django-json-widget
Author: José Manuel Rivas
Author-email: jmrivas86@gmail.com
License: MIT
Keywords: django-json-widget-copy
Platform: UNKNOWN
Classifier: Development Status :: 3 - Alpha
Classifier: Framework :: Django
Classifier: Framework :: Django :: 1.11
Classifier: Intended Audience :: Developers
Classifier: License :: OSI Approved :: BSD License
Classifier: Natural Language :: English
Classifier: Programming Language :: Python :: 2
Classifier: Programming Language :: Python :: 2.7
Classifier: Programming Language :: Python :: 3
Classifier: Programming Language :: Python :: 3.4
Classifier: Programming Language :: Python :: 3.5
Classifier: Programming Language :: Python :: 3.6
